py1password/__init__.py
py1password/_version.py
py1password/command_line.py
py1password/op.py
py1password/opssh.py
py1password-0.1.dist-info/LICENSE
py1password-0.1.dist-info/METADATA
py1password-0.1.dist-info/WHEEL
py1password-0.1.dist-info/entry_points.txt
py1password-0.1.dist-info/top_level.txt
py1password-0.1.dist-info/RECORD
