Metadata-Version: 2.1
Name: py1password
Version: 0.1
Summary: Python library for interfacing with 1password cli
Home-page: UNKNOWN
Author: Stuart B. Wilkins
Author-email: stuart@stuwilkins.org
License: UNKNOWN
Platform: UNKNOWN
